<Properties StartupConfiguration="{3B2D0A21-DB02-4111-B6E3-076D6256BF42}|Default">
  <MonoDevelop.Ide.ItemProperties.Statistics.Test PreferredExecutionTarget="MonoDevelop.Default" />
  <MonoDevelop.Ide.Workbench ActiveDocument="Statistics/StatsAlerter.cs">
    <Files>
      <File FileName="Statistics/Statistics.cs" Line="28" Column="10" />
      <File FileName="Statistics.Test/StatsUnitTest.cs" Line="1" Column="1" />
      <File FileName="Statistics/StatsGetSet.cs" Line="8" Column="40" />
      <File FileName="../Projects/EMICalculator/EMICalculator/InputVariables.cs" Line="12" Column="13" />
      <File FileName="Statistics/IAlerter.cs" Line="6" Column="18" />
      <File FileName="Statistics/EmailAlert.cs" Line="13" Column="30" />
      <File FileName="Statistics/LEDAlert.cs" Line="4" Column="35" />
      <File FileName="Statistics/StatsAlerter.cs" Line="13" Column="10" />
    </Files>
    <Pads>
      <Pad Id="ProjectPad">
        <State name="__root__">
          <Node name="statisticker" expanded="True">
            <Node name="Statistics" expanded="True">
              <Node name="Dependencies" expanded="True" />
            </Node>
            <Node name="Statistics.Test" expanded="True">
              <Node name="Dependencies" expanded="True" />
            </Node>
          </Node>
        </State>
      </Pad>
    </Pads>
  </MonoDevelop.Ide.Workbench>
  <MonoDevelop.Ide.DebuggingService.PinnedWatches />
  <MonoDevelop.Ide.Workspace ActiveConfiguration="Debug" />
  <MonoDevelop.Ide.DebuggingService.Breakpoints>
    <BreakpointStore />
  </MonoDevelop.Ide.DebuggingService.Breakpoints>
  <MultiItemStartupConfigurations />
</Properties>